MANIFEST.in
requirements.txt
setup.py
lisa/__init__.py
lisa/plugins/__init__.py
lisa/plugins/ProgrammeTV/README.rst
lisa/plugins/ProgrammeTV/__init__.py
lisa/plugins/ProgrammeTV/programmetv.json
lisa/plugins/ProgrammeTV/lang/fr/LC_MESSAGES/programmetv.mo
lisa/plugins/ProgrammeTV/lang/fr/LC_MESSAGES/programmetv.po
lisa/plugins/ProgrammeTV/modules/__init__.py
lisa/plugins/ProgrammeTV/modules/programmetv.py
lisa/plugins/ProgrammeTV/web/__init__.py
lisa/plugins/ProgrammeTV/web/api.py
lisa/plugins/ProgrammeTV/web/models.py
lisa/plugins/ProgrammeTV/web/tests.py
lisa/plugins/ProgrammeTV/web/urls.py
lisa/plugins/ProgrammeTV/web/views.py
lisa_plugin_ProgrammeTV.egg-info/PKG-INFO
lisa_plugin_ProgrammeTV.egg-info/SOURCES.txt
lisa_plugin_ProgrammeTV.egg-info/dependency_links.txt
lisa_plugin_ProgrammeTV.egg-info/namespace_packages.txt
lisa_plugin_ProgrammeTV.egg-info/requires.txt
lisa_plugin_ProgrammeTV.egg-info/top_level.txt